storage/__init__.py
storage/cloud_storage.py
woosailibrary/__init__.py
woosailibrary/core/__init__.py
woosailibrary/core/cache_manager.py
woosailibrary/core/lightweight_input.py
woosailibrary/core/number_compressor.py
woosailibrary/core/output_optimizer.py
woosailibrary/core/prompt_optimizer.py
woosailibrary/core/stats_tracker.py
woosailibrary/core/structured_schema.py
woosailibrary/tests/__init__.py
woosailibrary/tests/test_basic.py
woosailibrary/tests/test_license.py
woosailibrary/tools/__init__.py
woosailibrary/tools/license_generator.py
woosailibrary-1.1.0.dist-info/licenses/LICENSE
woosailibrary-1.1.0.dist-info/METADATA
woosailibrary-1.1.0.dist-info/WHEEL
woosailibrary-1.1.0.dist-info/top_level.txt
woosailibrary-1.1.0.dist-info/RECORD
