Metadata-Version: 2.4
Name: woosailibrary
Version: 1.1.0
Summary: AI Output Token Optimizer - Reduce OpenAI API costs by up to 88%
Home-page: https://github.com/woosai/woosailibrary
Author: WoosAI Team
Author-email: contact@woos-ai.com
Project-URL: Bug Reports, https://github.com/woosai/woosailibrary/issues
Project-URL: Documentation, https://github.com/woosai/woosailibrary#readme
Project-URL: Source, https://github.com/woosai/woosailibrary
Project-URL: Website, https://woos-ai.com
Keywords: openai,ai,optimization,cost-reduction,token-optimization,gpt,chatgpt,api,caching,statistics
Classifier: Development Status :: 4 - Beta
Classifier: Intended Audience :: Developers
Classifier: Topic :: Software Development :: Libraries :: Python Modules
Classifier: Topic :: Scientific/Engineering :: Artificial Intelligence
Classifier: License :: OSI Approved :: MIT License
Classifier: Programming Language :: Python :: 3
Classifier: Programming Language :: Python :: 3.7
Classifier: Programming Language :: Python :: 3.8
Classifier: Programming Language :: Python :: 3.9
Classifier: Programming Language :: Python :: 3.10
Classifier: Programming Language :: Python :: 3.11
Classifier: Operating System :: OS Independent
Requires-Python: >=3.7
License-File: LICENSE
Requires-Dist: openai>=1.3.0
Requires-Dist: tiktoken>=0.5.2
Requires-Dist: requests>=2.31.0
Requires-Dist: python-dotenv>=1.0.0
Provides-Extra: dev
Requires-Dist: pytest>=7.4.3; extra == "dev"
Requires-Dist: pytest-asyncio>=0.21.1; extra == "dev"
Dynamic: author
Dynamic: author-email
Dynamic: classifier
Dynamic: description
Dynamic: description-content-type
Dynamic: home-page
Dynamic: keywords
Dynamic: license-file
Dynamic: project-url
Dynamic: provides-extra
Dynamic: requires-dist
Dynamic: requires-python
Dynamic: summary
